{
  "project_info": {
    "project_number": "885865797051",
    "project_id": "plataforma-voluntariado-e45ce",
    "storage_bucket": "plataforma-voluntariado-e45ce.firebasestorage.app"
  },
  "client": [
    {
      "client_info": {
        "mobilesdk_app_id": "1:885865797051:android:9d9dcbf1940f6e8f9a609e",
        "android_client_info": {
          "package_name": "com.example.plataformavoluntariado"
        }
      },
      "oauth_client": [],
      "api_key": [
        {
          "current_key": "AIzaSyAfRae6fs12R_Efn7AtEchIGHF8srI25kM"
        }
      ],
      "services": {
        "appinvite_service": {
          "other_platform_oauth_client": []
        }
      }
    }
  ],
  "configuration_version": "1"
}